newport_motors/__init__.py
newport_motors/GUI/CustomNumeric.py
newport_motors/GUI/InstrumentGUI.py
newport_motors/GUI/LinearUI.py
newport_motors/GUI/TipTiltUI.py
newport_motors/Mocks/motor.py
newport_motors/Motors/instrument.py
newport_motors/Motors/motor.py
newport_motors/USBs/USBs.py
pyvisa_mock/__init__.py
newport_motors_py-0.1.3.dist-info/LICENSE
newport_motors_py-0.1.3.dist-info/METADATA
newport_motors_py-0.1.3.dist-info/WHEEL
newport_motors_py-0.1.3.dist-info/top_level.txt
newport_motors_py-0.1.3.dist-info/RECORD
