Metadata-Version: 2.1
Name: newport-motors-py
Version: 0.1.3
Summary: A python package for operating newport motors
Home-page: https://github.com/ataras2/newport_motors
Author: Adam Taras
Author-email: adam.taras@sydney.edu.au
Project-URL: Bug Tracker, https://github.com/ataras2/newport_motors/issues
Classifier: Programming Language :: Python :: 3
Classifier: Operating System :: OS Independent
License-File: LICENSE
Requires-Dist: pytest (==7.3.1)
Requires-Dist: streamlit (==1.22.0)
Requires-Dist: usbinfo (==1.1.2)
Requires-Dist: PyVISA (==1.13.0)
Requires-Dist: PyVISA-py (==0.6.3)
Requires-Dist: PyYAML (==6.0)
Requires-Dist: parse (==1.19.0)
Requires-Dist: visa (==1.0.0)
